yum/__init__.py
yum/admin.py
yum/apps.py
yum/models.py
yum/tests.py
yum/urls.py
yum/views.py
yum/migrations/0001_initial.py
yum/migrations/__init__.py
yum/templatetags/__init__.py
yum/templatetags/main_menu.py
YUM_menu_tree-0.0.1.dist-info/LICENSE
YUM_menu_tree-0.0.1.dist-info/METADATA
YUM_menu_tree-0.0.1.dist-info/WHEEL
YUM_menu_tree-0.0.1.dist-info/top_level.txt
YUM_menu_tree-0.0.1.dist-info/RECORD
